liat_ml_roberta/__init__.py
liat_ml_roberta/main.py
liat_ml_roberta/data/roberta_base_de_20190121_m10000_v24000_u500000/codes.txt
liat_ml_roberta/data/roberta_base_de_20190121_m10000_v24000_u500000/config.json
liat_ml_roberta/data/roberta_base_de_20190121_m10000_v24000_u500000/vocab.json
liat_ml_roberta/data/roberta_base_en_20190121_m10000_v24000_u125000/codes.txt
liat_ml_roberta/data/roberta_base_en_20190121_m10000_v24000_u125000/config.json
liat_ml_roberta/data/roberta_base_en_20190121_m10000_v24000_u125000/vocab.json
liat_ml_roberta/data/roberta_base_en_20190121_m10000_v24000_u500000/codes.txt
liat_ml_roberta/data/roberta_base_en_20190121_m10000_v24000_u500000/config.json
liat_ml_roberta/data/roberta_base_en_20190121_m10000_v24000_u500000/vocab.json
liat_ml_roberta/data/roberta_base_fr_20190121_m10000_v24000_u500000/codes.txt
liat_ml_roberta/data/roberta_base_fr_20190121_m10000_v24000_u500000/config.json
liat_ml_roberta/data/roberta_base_fr_20190121_m10000_v24000_u500000/vocab.json
liat_ml_roberta/data/roberta_base_ja_20190121_m10000_v24000_u125000/codes.txt
liat_ml_roberta/data/roberta_base_ja_20190121_m10000_v24000_u125000/config.json
liat_ml_roberta/data/roberta_base_ja_20190121_m10000_v24000_u125000/vocab.json
liat_ml_roberta/data/roberta_base_ja_20190121_m10000_v24000_u500000/codes.txt
liat_ml_roberta/data/roberta_base_ja_20190121_m10000_v24000_u500000/config.json
liat_ml_roberta/data/roberta_base_ja_20190121_m10000_v24000_u500000/vocab.json
liat_ml_roberta/data/roberta_large_en_20190121_m10000_v24000_u250000/codes.txt
liat_ml_roberta/data/roberta_large_en_20190121_m10000_v24000_u250000/config.json
liat_ml_roberta/data/roberta_large_en_20190121_m10000_v24000_u250000/vocab.json
liat_ml_roberta/tokenizers/__init__.py
liat_ml_roberta/tokenizers/tokenizers.py
liat_ml_roberta/utils/data.py
liat_ml_roberta-1.1.5.dist-info/METADATA
liat_ml_roberta-1.1.5.dist-info/WHEEL
liat_ml_roberta-1.1.5.dist-info/top_level.txt
liat_ml_roberta-1.1.5.dist-info/RECORD
