Metadata-Version: 2.1
Name: liat-ml-roberta
Version: 1.1.5
Summary: Multi-Launguage RoBERTa trained by RIKEN-AIP LIAT.
Home-page: https://github.com/k141303/liat_ml_roberta
Author: k141303
Author-email: kouta.nakayama@gmail.com
License: UNKNOWN
Download-URL: https://github.com/k141303/liat_ml_roberta
Platform: UNKNOWN
Requires-Dist: janome
Requires-Dist: subword-nmt
Requires-Dist: nltk
Requires-Dist: transformers
